{"lastId":6,"data":[{"description":"","dueDate":"","labels":["orange","red"],"comments":[],"activity":[],"subscribed":true,"title":"new title for this card 4 test","listId":1,"id":1},{"description":"#a description","dueDate":"","labels":"","comments":[],"activity":[],"subscribed":false,"title":"new title for this card 456 bailey boy","listId":2,"id":2},{"description":"#hello\n#hihi","dueDate":"","labels":"","comments":[],"activity":[],"subscribed":false,"title":"new title for this card 4678","listId":3,"id":3},{"description":"","dueDate":null,"labels":["green"],"comments":[],"activity":[],"subscribed":false,"title":"card title","listId":4,"id":4},{"description":"hi bailey","dueDate":"","labels":["orange","red"],"comments":[],"activity":[],"subscribed":false,"title":"bailey's world","listId":2,"id":5},{"description":"","dueDate":"","labels":["green","yellow"],"comments":[],"activity":[],"subscribed":false,"title":"card for list 5","listId":5,"id":6}]}